{"url": "https://www.who.int/csr/don/2001_12_13/en/", "date_of_publication": "2001-12-13", "headline": "2001 - Ebola haemorrhagic fever in Gabon - Update 3", "main_text": "As of 13 December The Gabon Ministry of Health has reported 14 suspected cases (2 laboratory confirmed) including 10 deaths.(see previous report). A team from MSF Belgium and EPICENTRE (both partners in the Global Outbreak Alert and Response Network) arrived in Libreville this morning to join international experts already in the country. The International Response Team met with the Ministry of Health in Libreville on Tuesday 11 December and assisted the Ministry of Health in completing the organizational and coordination arrangements for the response. This includes a Comit\u00e9 Politique Interminist\u00e9riel, Comit\u00e9 de Coordination Generale, Comit\u00e9 Provincial and Comit\u00e9 de Coordination Technique et Scientifique de Lutte with technical sub-committees for epidemiology and surveillance, case management, community sanitation and hygiene, health education, logistics and research. Technical meetings with the Gabonese health and military personnel were held on 12 December to organize the teams, their programme of work and the tools (e.g. epidemiologic forms and databases) and materials needed in the field. The joint Gabonese-International team is leaving for the field after making the necessary logistic preparations to travel to the outbreak site to establish an isolation unit and implement a surveillance system.", "key_terms": ["outbreak"]}