{"url": "https://www.who.int/csr/don/2003_05_07/en/", "date_of_publication": "2003-05-07", "headline": "Ebola haemorrhagic fever in the Republic of the Congo - Update 12", "main_text": "As of 6 May 2003, the Ministry of Health has reported 143 cases, including 128 deaths, in the districts of Mbomo and K\u00e9ll\u00e9 in Cuvette Ouest D\u00e9partement ( see previous report ). Thirteen of the cases are laboratory confirmed and 130 are epidemiologically linked. The two most recent deaths reported ocurred on the 22 April, one in the remote village of Ndjoukou (in K\u00e9ll\u00e9 district) and the other in a forest camp near K\u00e9ll\u00e9 town. Twenty-one contacts have been identified in Ndjoukou and K\u00e9ll\u00e9 town and are being visited on a regular basis by the surveillance team. The Ministry of Health and the Congolese Red Cross are continuing their activities (social mobilization, surveillance and case management) in the affected areas.", "key_terms": ["other"]}